pn4pm_nano/__init__.py
pn4pm_nano/petrinets.py
pn4pm_nano-0.0.6.2.dist-info/LICENSE
pn4pm_nano-0.0.6.2.dist-info/METADATA
pn4pm_nano-0.0.6.2.dist-info/WHEEL
pn4pm_nano-0.0.6.2.dist-info/pn4pm_nano-0.0.2.tar.gz
pn4pm_nano-0.0.6.2.dist-info/top_level.txt
pn4pm_nano-0.0.6.2.dist-info/RECORD
