Metadata-Version: 2.1
Name: pn4pm-nano
Version: 0.0.6.2
Summary: A small package for handling process models given as lists with their own row number and the row number of previous activityReturning a Petri Net for Process Mining / Conformance Checks
Home-page: https://github.com/DaMuBo/pn4pm
Author: Daniel Muller
Author-email: daniel.mueller@damu-analytics.com
License: UNKNOWN
Platform: UNKNOWN
Classifier: Programming Language :: Python :: 3
Classifier: License :: OSI Approved :: MIT License
Classifier: Operating System :: OS Independent
Requires-Python: >=3.6
